{"assets/fonts/netmarbleB.ttf":["assets/fonts/netmarbleB.ttf"],"assets/fonts/netmarbleL.ttf":["assets/fonts/netmarbleL.ttf"],"assets/fonts/netmarbleM.ttf":["assets/fonts/netmarbleM.ttf"],"assets/images/MSS_0004.jpg":["assets/images/MSS_0004.jpg"],"assets/images/MSS_0033.jpg":["assets/images/MSS_0033.jpg"],"assets/images/MSS_0063.jpg":["assets/images/MSS_0063.jpg"],"assets/map/apel_map.jpeg":["assets/map/apel_map.jpeg"],"packages/cupertino_icons/assets/CupertinoIcons.ttf":["packages/cupertino_icons/assets/CupertinoIcons.ttf"]}